bachclue/__init__.py
bachclue/bachclue.py
bachclue/.ipynb_checkpoints/__init__-checkpoint.py
bachclue/.ipynb_checkpoints/bachclue-checkpoint.py
bachclue-1.0.1.dist-info/METADATA
bachclue-1.0.1.dist-info/WHEEL
bachclue-1.0.1.dist-info/licenses/LICENSE
bachclue-1.0.1.dist-info/RECORD
