Metadata-Version: 2.4
Name: BaCHClue
Version: 1.0.1
Summary: BaCHClue helps to find the optimal resolution parameter for clustering scRNA-seq data analyzed with Scanpy, by calculating the BIC score or the Calinski-Harabasz score of each clustering given an interval of possible resolutions.
Project-URL: Homepage, https://gitbio.ens-lyon.fr/spatial-cell-id/bachclue
Author-email: Marco Uderzo <marco.uderzo@ens-lyon.fr>, Sergio Sarnataro <sergio.sarnataro@ens-lyon.fr>
License: GPL-3.0-or-later
License-File: LICENSE
Classifier: Operating System :: OS Independent
Classifier: Programming Language :: Python :: 3
Requires-Python: >=3.9
